coapshow/__init__.py
coapshow/blockwise.py
coapshow/credentials.py
coapshow/defaults.py
coapshow/error.py
coapshow/interfaces.py
coapshow/message.py
coapshow/messagemanager.py
coapshow/meta.py
coapshow/options.py
coapshow/optiontypes.py
coapshow/oscore.py
coapshow/oscore_sitewrapper.py
coapshow/pipe.py
coapshow/protocol.py
coapshow/resource.py
coapshow/tokenmanager.py
coapshow/cli/__init__.py
coapshow/cli/client.py
coapshow/cli/common.py
coapshow/cli/defaults.py
coapshow/cli/fileserver.py
coapshow/cli/proxy.py
coapshow/cli/rd.py
coapshow/numbers/__init__.py
coapshow/numbers/codes.py
coapshow/numbers/constants.py
coapshow/numbers/contentformat.py
coapshow/numbers/optionnumbers.py
coapshow/numbers/types.py
coapshow/proxy/__init__.py
coapshow/proxy/client.py
coapshow/proxy/server.py
coapshow/resourcedirectory/__init__.py
coapshow/resourcedirectory/client/__init__.py
coapshow/resourcedirectory/client/register.py
coapshow/transports/__init__.py
coapshow/transports/generic_udp.py
coapshow/transports/oscore.py
coapshow/transports/rfc8323common.py
coapshow/transports/simple6.py
coapshow/transports/simplesocketserver.py
coapshow/transports/tcp.py
coapshow/transports/tinydtls.py
coapshow/transports/tinydtls_server.py
coapshow/transports/tls.py
coapshow/transports/udp6.py
coapshow/transports/ws.py
coapshow/util/__init__.py
coapshow/util/cli.py
coapshow/util/contenttype.py
coapshow/util/cryptography_additions.py
coapshow/util/linkformat.py
coapshow/util/linkformat_pygments.py
coapshow/util/prettyprint.py
coapshow/util/pyodide_websockets.py
coapshow/util/socknumbers.py
coapshow/util/uri.py
coapshow/util/asyncio/__init__.py
coapshow/util/asyncio/getaddrinfo_addrconfig.py
coapshow/util/asyncio/recvmsg.py
coapshow/util/asyncio/timeoutdict.py
coapshow/util/vendored/link_header.py
coapshow-0.0.1.dist-info/LICENSE
coapshow-0.0.1.dist-info/METADATA
coapshow-0.0.1.dist-info/WHEEL
coapshow-0.0.1.dist-info/top_level.txt
coapshow-0.0.1.dist-info/RECORD
